Workbook

Sheet inputs
A1: id | B1: label | C1: value | D1: unit | E1: source_tag | F1: key
A2: F-001 | B2: 基準年の連結売上高 | C2: 2000 | D2: 億円 | E2: 公開 | F2: base_revenue
A3: F-227 | B3: 基準年の連結営業利益 | C3: 122.2 | D3: 億円 | E3: 公開 | F3: base_op
A4: F-011 | B4: 基準年末の純資産 | C4: 1150 | D4: 億円 | E4: 公開 | F4: base_equity
A5: F-230 | B5: 基準年末の有利子負債（期間中は一定） | C5: 400 | D5: 億円 | E5: 公開 | F5: base_debt
A6: F-229 | B6: 基準年末の現金及び預金 | C6: 320 | D6: 億円 | E6: 公開 | F6: base_cash
A7: S-006 | B7: 成り行きの売上成長率（市場成長の加重平均、gap-bridge） | C7: 4.9 | D7: % | E7: 推定 | F7: base_growth
A8: F-266 | B8: 成り行き事業の営業利益率（FY2025 の実績のまま） | C8: 6.11 | D8: % | E8: 推定 | F8: base_margin
A9: F-459 | B9: 施策売上の営業利益率（capital-capacity と同じ仮置き） | C9: 8 | D9: % | E9: 仮置き | F9: init_margin
A10: F-279 | B10: 成り行き売上に対する減価償却費の比率（FY2025） | C10: 4.5 | D10: % | E10: 推定 | F10: da_rate
A11: F-279 | B11: 成り行き売上に対する維持更新投資の比率（減価償却費と同じと置く。capital-capacity と同じ前提） | C11: 4.5 | D11: % | E11: 推定 | F11: maint_capex_rate
A12: F-466 | B12: 施策投資の償却年数 | C12: 10 | D12: 年 | E12: 仮置き | F12: dep_life
A13: F-460 | B13: 売上増加額に対する運転資本の増加率（capital-capacity と同じ仮置き） | C13: 15 | D13: % | E13: 仮置き | F13: nwc_rate
... A17: F-054 | B17: WACC | C17: 6 | D17: % | E17: 公開 | F17: wacc
B19: 施策の売上（05-initiatives.csv から。億円） | G19: FY2026 | H19: FY2027 | I19: FY2028 | J19: FY2029 | K19: FY2030
A20: I-001 | B20: EV 熱マネジメント部品の拡販 売上（確度 中） | D20: 億円 | E20: 推定 | F20: init_rev | G20: 41.9 | H20: 158.7 | I20: 309.6 | J20: 419.8 | K20: 482.7
A21: I-002 | B21: 半導体製造装置向け部品の能力増強 売上（確度 中） | D21: 億円 | E21: 推定 | F21: init_rev | G21: 40.4 | H21: 134.1 | I21: 194.3 | J21: 211.7 | K21: 230.8
A22: I-005 | B22: 産業用センサーの海外展開（現地の販売会社と提携） 売上（確度 中） | D22: 億円 | E22: 推定 | F22: init_rev | G22: 0 | H22: 26.2 | I22: 86.5 | J22: 124.7 | K22: 135.3
A23: I-006 | B23: 海外同業の中規模買収（1 件目） 売上（確度 低） | D23: 億円 | E23: 推定 | F23: init_rev | G23: 0 | H23: 0 | I23: 0 | J23: 400 | K23: 420
B25: 施策の投資（05-initiatives.csv から。億円） | G25: FY2026 | H25: FY2027 | I25: FY2028 | J25: FY2029 | K25: FY2030
A26: I-001 | B26: EV 熱マネジメント部品の拡販 投資（確度 中） | D26: 億円 | E26: 推定 | F26: init_inv | G26: 120 | H26: 120 | I26: 60 | J26: 0 | K26: 0
A27: I-002 | B27: 半導体製造装置向け部品の能力増強 投資（確度 中） | D27: 億円 | E27: 推定 | F27: init_inv | G27: 100 | H27: 100 | I27: 0 | J27: 0 | K27: 0
A28: I-005 | B28: 産業用センサーの海外展開（現地の販売会社と提携） 投資（確度 中） | D28: 億円 | E28: 推定 | F28: init_inv | G28: 30 | H28: 30 | I28: 0 | J28: 0 | K28: 0
A29: I-006 | B29: 海外同業の中規模買収（1 件目） 投資（確度 低） | D29: 億円 | E29: 推定 | F29: init_inv | G29: 0 | H29: 0 | I29: 0 | J29: 480 | K29: 0

Sheet calc
A1: 項目 | B1: 単位 | C1: FY2025（実績） | D1: FY2026 | E1: FY2027 | F1: FY2028 | G1: FY2029 | H1: FY2030
A2: 成り行き売上 | B2: 億円 | C2: =inputs!$C$2 -> 2000 | D2: =C2*(1+inputs!$C$7%) -> 2098 | E2: =D2*(1+inputs!$C$7%) -> 2200.802 | F2: =E2*(1+inputs!$C$7%) -> 2308.6413 | G2: =F2*(1+inputs!$C$7%) -> 2421.7647 | H2: =G2*(1+inputs!$C$7%) -> 2540.4312
A3: 施策売上 | B3: 億円 | D3: =SUM(inputs!G20:G23) -> 82.3 | E3: =SUM(inputs!H20:H23) -> 319 | F3: =SUM(inputs!I20:I23) -> 590.4 | G3: =SUM(inputs!J20:J23) -> 1156.2 | H3: =SUM(inputs!K20:K23) -> 1268.8
A4: 連結売上高 | B4: 億円 | C4: =C2 -> 2000 | D4: =D2+D3 -> 2180.3 | E4: =E2+E3 -> 2519.802 | F4: =F2+F3 -> 2899.0413 | G4: =G2+G3 -> 3577.9647 | H4: =H2+H3 -> 3809.2312
A5: 成り行き営業利益 | B5: 億円 | D5: =D2*inputs!$C$8% -> 128.1878 | E5: =E2*inputs!$C$8% -> 134.469 | F5: =F2*inputs!$C$8% -> 141.05798 | G5: =G2*inputs!$C$8% -> 147.96982 | H5: =H2*inputs!$C$8% -> 155.22035
A6: 施策営業利益 | B6: 億円 | D6: =D3*inputs!$C$9% -> 6.584 | E6: =E3*inputs!$C$9% -> 25.52 | F6: =F3*inputs!$C$9% -> 47.232 | G6: =G3*inputs!$C$9% -> 92.496 | H6: =H3*inputs!$C$9% -> 101.504
A7: 営業利益 | B7: 億円 | C7: =inputs!$C$3 -> 122.2 | D7: =D5+D6 -> 134.7718 | E7: =E5+E6 -> 159.989 | F7: =F5+F6 -> 188.28998 | G7: =G5+G6 -> 240.46582 | H7: =H5+H6 -> 256.72435
A8: 営業利益率 | B8: % | C8: =C7/C4 -> 0.0611 | D8: =D7/D4 -> 0.06181342 | E8: =E7/E4 -> 0.063492688 | F8: =F7/F4 -> 0.064949052 | G8: =G7/G4 -> 0.067207433 | H8: =H7/H4 -> 0.067395318
A9: 減価償却費（成り行き） | B9: 億円 | D9: =D2*inputs!$C$10% -> 94.41 | E9: =E2*inputs!$C$10% -> 99.03609 | F9: =F2*inputs!$C$10% -> 103.88886 | G9: =G2*inputs!$C$10% -> 108.97941 | H9: =H2*inputs!$C$10% -> 114.3194
A10: 減価償却費（施策投資） | B10: 億円 | E10: =SUM(inputs!$G$26:G29)/inputs!$C$12 -> 25 | F10: =SUM(inputs!$G$26:H29)/inputs!$C$12 -> 50 | G10: =SUM(inputs!$G$26:I29)/inputs!$C$12 -> 56 | H10: =SUM(inputs!$G$26:J29)/inputs!$C$12 -> 104
A11: 減価償却費 | B11: 億円 | D11: =D9+D10 -> 94.41 | E11: =E9+E10 -> 124.03609 | F11: =F9+F10 -> 153.88886 | G11: =G9+G10 -> 164.97941 | H11: =H9+H10 -> 218.3194
A12: 維持更新投資 | B12: 億円 | D12: =D2*inputs!$C$11% -> 94.41 | E12: =E2*inputs!$C$11% -> 99.03609 | F12: =F2*inputs!$C$11% -> 103.88886 | G12: =G2*inputs!$C$11% -> 108.97941 | H12: =H2*inputs!$C$11% -> 114.3194
A13: 施策投資 | B13: 億円 | D13: =SUM(inputs!G26:G29) -> 250 | E13: =SUM(inputs!H26:H29) -> 250 | F13: =SUM(inputs!I26:I29) -> 60 | G13: =SUM(inputs!J26:J29) -> 480 | H13: =SUM(inputs!K26:K29) -> 0
A14: 投資合計 | B14: 億円 | D14: =D12+D13 -> 344.41 | E14: =E12+E13 -> 349.03609 | F14: =F12+F13 -> 163.88886 | G14: =G12+G13 -> 588.97941 | H14: =H12+H13 -> 114.3194
A15: 運転資本の増加 | B15: 億円 | D15: =(D4-C4)*inputs!$C$13% -> 27.045 | E15: =(E4-D4)*inputs!$C$13% -> 50.9253 | F15: =(F4-E4)*inputs!$C$13% -> 56.885895 | G15: =(G4-F4)*inputs!$C$13% -> 101.83851 | H15: =(H4-G4)*inputs!$C$13% -> 34.689971
A16: 営業利益に対する税金 | B16: 億円 | D16: =D7*inputs!$C$14% -> 40.43154 | E16: =E7*inputs!$C$14% -> 47.996701 | F16: =F7*inputs!$C$14% -> 56.486995 | G16: =G7*inputs!$C$14% -> 72.139747 | H16: =H7*inputs!$C$14% -> 77.017304
A17: NOPAT | B17: 億円 | D17: =D7-D16 -> 94.34026 | E17: =E7-E16 -> 111.9923 | F17: =F7-F16 -> 131.80299 | G17: =G7-G16 -> 168.32608 | H17: =H7-H16 -> 179.70704
A18: フリー・キャッシュ・フロー | B18: 億円 | D18: =D17+D11-D14-D15 -> -182.70474 | E18: =E17+E11-E14-E15 -> -163.933 | F18: =F17+F11-F14-F15 -> 64.917094 | G18: =G17+G11-G14-G15 -> -357.51244 | H18: =H17+H11-H14-H15 -> 249.01707
A19: 投下資本（期末） | B19: 億円 | C19: =inputs!$C$4+inputs!$C$5-inputs!$C$6 -> 1230 | D19: =C19+D14-D11+D15 -> 1507.045 | E19: =D19+E14-E11+E15 -> 1782.9703 | F19: =E19+F14-F11+F15 -> 1849.8562 | G19: =F19+G14-G11+G15 -> 2375.6947 | H19: =G19+H14-H11+H15 -> 2306.3847
A20: ROIC（期首期末平均の投下資本） | B20: % | D20: =D17/AVERAGE(C19,D19) -> 0.068935849 | E20: =E17/AVERAGE(D19,E19) -> 0.06808011 | F20: =F17/AVERAGE(E19,F19) -> 0.072562226 | G20: =G17/AVERAGE(F19,G19) -> 0.079670595 | H20: =H17/AVERAGE(G19,H19) -> 0.076763774
A21: ROIC − WACC | B21: % | D21: =D20-inputs!$C$17% -> 0.0089358487 | E21: =E20-inputs!$C$17% -> 0.0080801099 | F21: =F20-inputs!$C$17% -> 0.012562226 | G21: =G20-inputs!$C$17% -> 0.019670595 | H21: =H20-inputs!$C$17% -> 0.016763774
A22: NOPAT マージン | B22: % | D22: =D17/D4 -> 0.043269394 | E22: =E17/E4 -> 0.044444882 | F22: =F17/F4 -> 0.045464336 | G22: =G17/G4 -> 0.047045203 | H22: =H17/H4 -> 0.047176722
A23: 投下資本回転率 | B23: 倍 | D23: =D4/AVERAGE(C19,D19) -> 1.593178 | E23: =E4/AVERAGE(D19,E19) -> 1.5317874 | F23: =F4/AVERAGE(E19,F19) -> 1.5960252 | G23: =G4/AVERAGE(F19,G19) -> 1.6934903 | H23: =H4/AVERAGE(G19,H19) -> 1.6271536
A24: 支払利息 | B24: 億円 | D24: =inputs!$C$5*inputs!$C$15% -> 4 | E24: =inputs!$C$5*inputs!$C$15% -> 4 | F24: =inputs!$C$5*inputs!$C$15% -> 4 | G24: =inputs!$C$5*inputs!$C$15% -> 4 | H24: =inputs!$C$5*inputs!$C$15% -> 4
A25: 当期純利益（近似） | B25: 億円 | D25: =(D7-D24)*(1-inputs!$C$14%) -> 91.54026 | E25: =(E7-E24)*(1-inputs!$C$14%) -> 109.1923 | F25: =(F7-F24)*(1-inputs!$C$14%) -> 129.00299 | G25: =(G7-G24)*(1-inputs!$C$14%) -> 165.52608 | H25: =(H7-H24)*(1-inputs!$C$14%) -> 176.90704
A26: 配当金 | B26: 億円 | D26: =D25*inputs!$C$16% -> 32.039091 | E26: =E25*inputs!$C$16% -> 38.217306 | F26: =F25*inputs!$C$16% -> 45.151046 | G26: =G25*inputs!$C$16% -> 57.934127 | H26: =H25*inputs!$C$16% -> 61.917465
A27: 純資産（期末） | B27: 億円 | C27: =inputs!$C$4 -> 1150 | D27: =C27+D25-D26 -> 1209.5012 | E27: =D27+E25-E26 -> 1280.4762 | F27: =E27+F25-F26 -> 1364.3281 | G27: =F27+G25-G26 -> 1471.9201 | H27: =G27+H25-H26 -> 1586.9096
A28: ROE（近似、期首期末平均） | B28: % | D28: =D25/AVERAGE(C27,D27) -> 0.077592892 | E28: =E25/AVERAGE(D27,E27) -> 0.087705458 | F28: =F25/AVERAGE(E27,F27) -> 0.097552011 | G28: =G25/AVERAGE(F27,G27) -> 0.11672186 | H28: =H25/AVERAGE(G27,H27) -> 0.11566976
A29: 現金及び預金（期末、借入一定） | B29: 億円 | C29: =inputs!$C$6 -> 320 | D29: =C29+D18-D24*(1-inputs!$C$14%)-D26 -> 102.45617 | E29: =D29+E18-E24*(1-inputs!$C$14%)-E26 -> -102.49413 | F29: =E29+F18-F24*(1-inputs!$C$14%)-F26 -> -85.528087 | G29: =F29+G18-G24*(1-inputs!$C$14%)-G26 -> -503.77465 | H29: =G29+H18-H24*(1-inputs!$C$14%)-H26 -> -319.47504
A30: ネット D/E レシオ | B30: 倍 | C30: =(inputs!$C$5-C29)/C27 -> 0.069565217 | D30: =(inputs!$C$5-D29)/D27 -> 0.24600541 | E30: =(inputs!$C$5-E29)/E27 -> 0.39242756 | F30: =(inputs!$C$5-F29)/F27 -> 0.3558734 | G30: =(inputs!$C$5-G29)/G27 -> 0.61401069 | H30: =(inputs!$C$5-H29)/H27 -> 0.45338123
